osvmoverview/__init__.py
osvmoverview/dashboard.py
osvmoverview/overview/__init__.py
osvmoverview/overview/panel.py
osvmoverview/overview/tables.py
osvmoverview/overview/tabs.py
osvmoverview/overview/tests.py
osvmoverview/overview/urls.py
osvmoverview/overview/views.py
vmoverview/__init__.py
vmoverview/dashboard.py
vmoverview/overview/__init__.py
vmoverview/overview/panel.py
vmoverview/overview/tables.py
vmoverview/overview/tabs.py
vmoverview/overview/tests.py
vmoverview/overview/urls.py
vmoverview/overview/views.py
vmoverview/overview/templates/overview/detail.html
vmoverview/overview/templates/overview/index.html
vmoverview/static/vmoverview/js/vmoverview.js
vmoverview/static/vmoverview/scss/vmoverview.scss
vmoverview/templates/vmoverview/base.html
osvmoverview-1.0.0.dist-info/AUTHORS
osvmoverview-1.0.0.dist-info/LICENSE
osvmoverview-1.0.0.dist-info/METADATA
osvmoverview-1.0.0.dist-info/WHEEL
osvmoverview-1.0.0.dist-info/pbr.json
osvmoverview-1.0.0.dist-info/top_level.txt
osvmoverview-1.0.0.dist-info/RECORD
