Metadata-Version: 2.1
Name: osvmoverview
Version: 1.0.0
Summary: Openstack VM overview Horizon plugin
Home-page: http://www.openstack.org/
Author: Olivier Sallou
Author-email: olivier.sallou@irisa.fr
License: UNKNOWN
Platform: UNKNOWN
Classifier: Environment :: OpenStack
Classifier: Intended Audience :: Information Technology
Classifier: Intended Audience :: System Administrators
Classifier: License :: OSI Approved :: Apache Software License
Classifier: Operating System :: POSIX :: Linux
Classifier: Programming Language :: Python
Classifier: Programming Language :: Python :: 3
Classifier: Programming Language :: Python :: 3.5
